rstms_ehandler/__init__.py
rstms_ehandler/ehandler.py
rstms_ehandler/example.py
rstms_ehandler/version.py
rstms_ehandler-0.0.3.dist-info/entry_points.txt
rstms_ehandler-0.0.3.dist-info/LICENSE
rstms_ehandler-0.0.3.dist-info/WHEEL
rstms_ehandler-0.0.3.dist-info/METADATA
rstms_ehandler-0.0.3.dist-info/RECORD
